ss_hankel/__init__.py
ss_hankel/__main__.py
ss_hankel/_main.py
ss_hankel/_score.py
ss_hankel/cli.py
ss_hankel/py.typed
ss_hankel/testing.py
ss_hankel-1.0.0.dist-info/licenses/LICENSE
ss_hankel-1.0.0.dist-info/METADATA
ss_hankel-1.0.0.dist-info/WHEEL
ss_hankel-1.0.0.dist-info/entry_points.txt
ss_hankel-1.0.0.dist-info/top_level.txt
ss_hankel-1.0.0.dist-info/RECORD
