Metadata-Version: 2.4
Name: ss-hankel
Version: 1.0.0
Summary: Derivative-free method to find zeros of analytic (holomorphic) functions / solve nonlinear (polynomial / generalized) eigenvalue problems using contour integration. (Block SS-Hankel method, Block Sakurai Sugiura method)
Author-email: 34j <34j.95a2p@simplelogin.com>
License: MIT
Project-URL: Bug Tracker, https://github.com/34j/ss-hankel/issues
Project-URL: Changelog, https://github.com/34j/ss-hankel/blob/main/CHANGELOG.md
Project-URL: documentation, https://ss-hankel.readthedocs.io
Project-URL: repository, https://github.com/34j/ss-hankel
Classifier: Development Status :: 2 - Pre-Alpha
Classifier: Intended Audience :: Developers
Classifier: Natural Language :: English
Classifier: Operating System :: OS Independent
Classifier: Programming Language :: Python :: 3.10
Classifier: Programming Language :: Python :: 3.11
Classifier: Programming Language :: Python :: 3.12
Classifier: Programming Language :: Python :: 3.13
Classifier: Topic :: Software Development :: Libraries
Requires-Python: >=3.10
License-File: LICENSE
Requires-Dist: attrs>=25.3.0
Requires-Dist: cyclopts>=3.14.2
Requires-Dist: rich>=10
Requires-Dist: scipy>=1.13.1
Requires-Dist: sympy>=1.14.0
Requires-Dist: typing-extensions>=4.13.2
Dynamic: license-file
